universities_api_wrapper/__init__.py
universities_api_wrapper-0.0.5.dist-info/LICENSE.txt
universities_api_wrapper-0.0.5.dist-info/METADATA
universities_api_wrapper-0.0.5.dist-info/WHEEL
universities_api_wrapper-0.0.5.dist-info/top_level.txt
universities_api_wrapper-0.0.5.dist-info/RECORD
